castl/__init__.py
castl/h5grid.py
castl/mcfit.py
castl-0.6.1.dist-info/LICENSE
castl-0.6.1.dist-info/METADATA
castl-0.6.1.dist-info/WHEEL
castl-0.6.1.dist-info/top_level.txt
castl-0.6.1.dist-info/RECORD
