Metadata-Version: 2.1
Name: castl
Version: 0.6.1
Summary: Computional Analysis of Spectral TempLates
Home-page: https://github.com/huntbrooks85/castl
Author: Hunter Brooks
Author-email: hcb98@nau.edu
License: MIT License
Classifier: Programming Language :: Python :: 3
Classifier: License :: OSI Approved :: MIT License
Classifier: Operating System :: OS Independent
Requires-Python: >=3.6
License-File: LICENSE
Requires-Dist: emcee
Requires-Dist: pathos
Requires-Dist: IPython
Requires-Dist: tqdm
Requires-Dist: h5py
Requires-Dist: astropy
Requires-Dist: pandas
Requires-Dist: matplotlib
Requires-Dist: corner
Requires-Dist: scikit-learn
Requires-Dist: scipy
Requires-Dist: numpy
Requires-Dist: xarray
